autoimport-1.6.1.dist-info/METADATA
autoimport-1.6.1.dist-info/WHEEL
autoimport-1.6.1.dist-info/entry_points.txt
autoimport-1.6.1.dist-info/licenses/LICENSE
autoimport/__init__.py
autoimport/__main__.py
autoimport/entrypoints/__init__.py
autoimport/entrypoints/cli.py
autoimport/model.py
autoimport/py.typed
autoimport/services.py
autoimport/version.py
autoimport-1.6.1.dist-info/RECORD
