Metadata-Version: 2.1
Name: autoimport
Version: 1.6.1
Summary: Autoimport missing python libraries.
Home-page: https://github.com/lyz-code/autoimport
Author-Email: Lyz <lyz@riseup.net>
License: GPL-3.0-only
Classifier: Development Status :: 5 - Production/Stable
Classifier: Intended Audience :: Developers
Classifier: License :: OSI Approved :: GNU General Public License v3 (GPLv3)
Classifier: Operating System :: Unix
Classifier: Operating System :: POSIX
Classifier: Programming Language :: Python
Classifier: Programming Language :: Python :: 3
Classifier: Programming Language :: Python :: 3.8
Classifier: Programming Language :: Python :: 3.9
Classifier: Programming Language :: Python :: 3.10
Classifier: Programming Language :: Python :: 3.11
Classifier: Topic :: Utilities
Classifier: Natural Language :: English
Project-URL: Issues, https://github.com/lyz-code/autoimport/issues
Project-URL: Homepage, https://github.com/lyz-code/autoimport
Project-URL: Documentation, https://lyz-code.github.io/autoimport
Requires-Python: >=3.8
Requires-Dist: click>=8.1.3
Requires-Dist: autoflake>=1.4
Requires-Dist: pyprojroot>=0.2.0
Requires-Dist: sh>=1.14.2
Requires-Dist: maison<2.0.0,>=1.4.0
Requires-Dist: xdg>=6.0.0
